Metadata-Version: 1.0
Name: pyramid-soap
Version: 0.2
Summary: Soap for pyramid.
Home-page: https://bitbucket.org/artgins/pyramid_soap
Author: Gines Martinez Sanchez
Author-email: ginsmar@artgins.com
License: MIT
Keywords: web pyramid pylons soap soapbox
Platform: UNKNOWN
Classifier: Programming Language :: Python
Classifier: Framework :: Pyramid
Classifier: License :: OSI Approved :: MIT License
Classifier: Topic :: Internet :: WWW/HTTP
Classifier: Topic :: Internet :: WWW/HTTP :: WSGI :: Application
